{
    "0": {
        "accuracy": 0.0,
        "avg_joules": 4.264453222749806,
        "battery": 37352.700000000004,
        "comm_latency": 5.470907643379839,
        "delta_infer_battery": 18.99108327945695,
        "delta_train_battery": 32.68241990176437,
        "inference_latency": 1.6052862942976505,
        "last_round": 0,
        "max_battery": 48510.0,
        "min_battery": 21829.5,
        "times_selected": 0,
        "total_inference_latency": 7.076193937677489,
        "total_train_latency": 10.286766526272789,
        "train_latency": 4.815858882892951,
        "trans_prob": 1,
        "utility": 37352.700000000004
    },
    "1": {
        "accuracy": 0.0,
        "avg_joules": 4.23357530908584,
        "battery": 22730.399999999998,
        "comm_latency": 5.525782656530641,
        "delta_infer_battery": 27.992728620339115,
        "delta_train_battery": 59.4437108660213,
        "inference_latency": 3.714470624649574,
        "last_round": 0,
        "max_battery": 55440.0,
        "min_battery": 24948.0,
        "times_selected": 0,
        "total_inference_latency": 9.240253281180214,
        "total_train_latency": 16.669194530479363,
        "train_latency": 11.143411873948722,
        "trans_prob": 1,
        "utility": 22730.399999999998
    },
    "2": {
        "accuracy": 0.0,
        "avg_joules": 4.909321760398379,
        "battery": 41718.6,
        "comm_latency": 5.292352520242429,
        "delta_infer_battery": 12.081328247070669,
        "delta_train_battery": 12.745939551335619,
        "inference_latency": 0.06768870902149007,
        "last_round": 0,
        "max_battery": 48510.0,
        "min_battery": 21829.5,
        "times_selected": 0,
        "total_inference_latency": 5.360041229263919,
        "total_train_latency": 5.495418647306899,
        "train_latency": 0.20306612706447022,
        "trans_prob": 1,
        "utility": 41718.6
    },
    "3": {
        "accuracy": 0.0,
        "avg_joules": 3.3663209998842456,
        "battery": 46084.5,
        "comm_latency": 5.144981159022785,
        "delta_infer_battery": 14.316516166470592,
        "delta_train_battery": 20.105832153350605,
        "inference_latency": 0.8598876915004668,
        "last_round": 0,
        "max_battery": 48510.0,
        "min_battery": 21829.5,
        "times_selected": 0,
        "total_inference_latency": 6.004868850523252,
        "total_train_latency": 7.724644233524185,
        "train_latency": 2.5796630745014006,
        "trans_prob": 1,
        "utility": 46084.5
    },
    "4": {
        "accuracy": 0.0,
        "avg_joules": 4.590107079822982,
        "battery": 23839.2,
        "comm_latency": 5.991437787694187,
        "delta_infer_battery": 14.628626932392644,
        "delta_train_battery": 17.28389701981574,
        "inference_latency": 0.2892383599388163,
        "last_round": 0,
        "max_battery": 55440.0,
        "min_battery": 24948.0,
        "times_selected": 0,
        "total_inference_latency": 6.280676147633003,
        "total_train_latency": 6.859152867510636,
        "train_latency": 0.8677150798164489,
        "trans_prob": 1,
        "utility": 23839.2
    },
    "5": {
        "accuracy": 0.0,
        "avg_joules": 4.110916699242213,
        "battery": 27720.0,
        "comm_latency": 6.086032348267855,
        "delta_infer_battery": 14.185850661502585,
        "delta_train_battery": 15.535568358198475,
        "inference_latency": 0.16416261815092134,
        "last_round": 0,
        "max_battery": 55440.0,
        "min_battery": 24948.0,
        "times_selected": 0,
        "total_inference_latency": 6.250194966418777,
        "total_train_latency": 6.578520202720619,
        "train_latency": 0.49248785445276405,
        "trans_prob": 1,
        "utility": 27720.0
    },
    "6": {
        "accuracy": 0.0,
        "avg_joules": 3.010105532798753,
        "battery": 46569.6,
        "comm_latency": 5.096315161488895,
        "delta_infer_battery": 12.413605244523946,
        "delta_train_battery": 14.613176416561144,
        "inference_latency": 0.36536446115762405,
        "last_round": 0,
        "max_battery": 48510.0,
        "min_battery": 21829.5,
        "times_selected": 0,
        "total_inference_latency": 5.4616796226465185,
        "total_train_latency": 6.192408544961767,
        "train_latency": 1.096093383472872,
        "trans_prob": 1,
        "utility": 46569.6
    },
    "7": {
        "accuracy": 0.0,
        "avg_joules": 3.8627418184306785,
        "battery": 38808.0,
        "comm_latency": 5.546034756407592,
        "delta_infer_battery": 14.059110026686417,
        "delta_train_battery": 17.552935761609536,
        "inference_latency": 0.45224686235211053,
        "last_round": 0,
        "max_battery": 48510.0,
        "min_battery": 21829.5,
        "times_selected": 0,
        "total_inference_latency": 5.998281618759703,
        "total_train_latency": 6.902775343463924,
        "train_latency": 1.3567405870563316,
        "trans_prob": 1,
        "utility": 38808.0
    },
    "8": {
        "accuracy": 0.0,
        "avg_joules": 4.747437002495573,
        "battery": 37352.700000000004,
        "comm_latency": 5.172751336997055,
        "delta_infer_battery": 18.34721919547227,
        "delta_train_battery": 32.074641650149886,
        "inference_latency": 1.4457719446789452,
        "last_round": 0,
        "max_battery": 48510.0,
        "min_battery": 21829.5,
        "times_selected": 0,
        "total_inference_latency": 6.6185232816760005,
        "total_train_latency": 9.51006717103389,
        "train_latency": 4.337315834036835,
        "trans_prob": 1,
        "utility": 37352.700000000004
    },
    "9": {
        "accuracy": 0.0,
        "avg_joules": 4.638592255284939,
        "battery": 51004.8,
        "comm_latency": 6.124778343974516,
        "delta_infer_battery": 21.93521184736953,
        "delta_train_battery": 38.61161969486174,
        "inference_latency": 1.7975720789526273,
        "last_round": 0,
        "max_battery": 55440.0,
        "min_battery": 24948.0,
        "times_selected": 0,
        "total_inference_latency": 7.922350422927143,
        "total_train_latency": 11.517494580832398,
        "train_latency": 5.392716236857882,
        "trans_prob": 1,
        "utility": 51004.8
    },
    "10": {
        "accuracy": 0.0,
        "avg_joules": 3.615851461738801,
        "battery": 18295.2,
        "comm_latency": 5.530738457786592,
        "delta_infer_battery": 15.81396378479629,
        "delta_train_battery": 22.885412601816398,
        "inference_latency": 0.9778400595055929,
        "last_round": 0,
        "max_battery": 55440.0,
        "min_battery": 24948.0,
        "times_selected": 0,
        "total_inference_latency": 6.508578517292185,
        "total_train_latency": 8.46425863630337,
        "train_latency": 2.933520178516779,
        "trans_prob": 1,
        "utility": 18295.2
    },
    "11": {
        "accuracy": 0.0,
        "avg_joules": 3.8670067739476552,
        "battery": 43659.0,
        "comm_latency": 5.2161325889918455,
        "delta_infer_battery": 26.56851187692316,
        "delta_train_battery": 56.54590693564568,
        "inference_latency": 3.8760463597688415,
        "last_round": 0,
        "max_battery": 48510.0,
        "min_battery": 21829.5,
        "times_selected": 0,
        "total_inference_latency": 9.092178948760687,
        "total_train_latency": 16.84427166829837,
        "train_latency": 11.628139079306525,
        "trans_prob": 1,
        "utility": 43659.0
    },
    "12": {
        "accuracy": 0.0,
        "avg_joules": 2.203577490454025,
        "battery": 24255.0,
        "comm_latency": 5.805736813291063,
        "delta_infer_battery": 13.73809493723018,
        "delta_train_battery": 15.436813360678212,
        "inference_latency": 0.385445583558314,
        "last_round": 0,
        "max_battery": 69300.0,
        "min_battery": 31185.0,
        "times_selected": 0,
        "total_inference_latency": 6.191182396849378,
        "total_train_latency": 6.962073563966006,
        "train_latency": 1.156336750674942,
        "trans_prob": 1,
        "utility": 24255.0
    },
    "13": {
        "accuracy": 0.0,
        "avg_joules": 2.828219920629203,
        "battery": 43035.299999999996,
        "comm_latency": 4.9865462614238325,
        "delta_infer_battery": 22.35933456337493,
        "delta_train_battery": 44.937738289402965,
        "inference_latency": 3.9916280133202924,
        "last_round": 0,
        "max_battery": 62370.0,
        "min_battery": 28066.5,
        "times_selected": 0,
        "total_inference_latency": 8.978174274744125,
        "total_train_latency": 16.96143030138471,
        "train_latency": 11.974884039960877,
        "trans_prob": 1,
        "utility": 43035.299999999996
    },
    "14": {
        "accuracy": 0.0,
        "avg_joules": 4.492212742662909,
        "battery": 49896.0,
        "comm_latency": 5.029917682476045,
        "delta_infer_battery": 11.63004566139295,
        "delta_train_battery": 12.557302473985208,
        "inference_latency": 0.10320713484760245,
        "last_round": 0,
        "max_battery": 62370.0,
        "min_battery": 28066.5,
        "times_selected": 0,
        "total_inference_latency": 5.1331248173236474,
        "total_train_latency": 5.339539087018852,
        "train_latency": 0.30962140454280734,
        "trans_prob": 1,
        "utility": 49896.0
    },
    "15": {
        "accuracy": 0.0,
        "avg_joules": 3.342941997902323,
        "battery": 24740.100000000002,
        "comm_latency": 6.082744255001992,
        "delta_infer_battery": 21.664631421783316,
        "delta_train_battery": 37.9865097731411,
        "inference_latency": 2.4412446224911575,
        "last_round": 0,
        "max_battery": 48510.0,
        "min_battery": 21829.5,
        "times_selected": 0,
        "total_inference_latency": 8.52398887749315,
        "total_train_latency": 13.406478122475464,
        "train_latency": 7.323733867473472,
        "trans_prob": 1,
        "utility": 24740.100000000002
    },
    "16": {
        "accuracy": 0.0,
        "avg_joules": 2.6190222047371527,
        "battery": 35343.0,
        "comm_latency": 6.0902920905953275,
        "delta_infer_battery": 17.17226015507361,
        "delta_train_battery": 24.47588358297757,
        "inference_latency": 1.394341639160894,
        "last_round": 0,
        "max_battery": 69300.0,
        "min_battery": 31185.0,
        "times_selected": 0,
        "total_inference_latency": 7.484633729756221,
        "total_train_latency": 10.27331700807801,
        "train_latency": 4.183024917482682,
        "trans_prob": 1,
        "utility": 35343.0
    },
    "17": {
        "accuracy": 0.0,
        "avg_joules": 3.746396284164459,
        "battery": 65141.99999999999,
        "comm_latency": 5.417084271186384,
        "delta_infer_battery": 19.752230084898912,
        "delta_train_battery": 35.2048360906292,
        "inference_latency": 2.0623293471444124,
        "last_round": 0,
        "max_battery": 69300.0,
        "min_battery": 31185.0,
        "times_selected": 0,
        "total_inference_latency": 7.4794136183307955,
        "total_train_latency": 11.604072312619621,
        "train_latency": 6.186988041433238,
        "trans_prob": 1,
        "utility": 65141.99999999999
    },
    "18": {
        "accuracy": 0.0,
        "avg_joules": 4.209122286196894,
        "battery": 28620.899999999998,
        "comm_latency": 4.992556521297946,
        "delta_infer_battery": 12.246787266594396,
        "delta_train_battery": 14.573410845220305,
        "inference_latency": 0.2763787103852599,
        "last_round": 0,
        "max_battery": 48510.0,
        "min_battery": 21829.5,
        "times_selected": 0,
        "total_inference_latency": 5.268935231683206,
        "total_train_latency": 5.821692652453725,
        "train_latency": 0.8291361311557797,
        "trans_prob": 1,
        "utility": 28620.899999999998
    },
    "19": {
        "accuracy": 0.0,
        "avg_joules": 4.123457491506982,
        "battery": 17186.4,
        "comm_latency": 5.609431022790069,
        "delta_infer_battery": 14.21262985316613,
        "delta_train_battery": 17.732015818310476,
        "inference_latency": 0.4267518183942927,
        "last_round": 0,
        "max_battery": 55440.0,
        "min_battery": 24948.0,
        "times_selected": 0,
        "total_inference_latency": 6.036182841184362,
        "total_train_latency": 6.889686477972948,
        "train_latency": 1.2802554551828782,
        "trans_prob": 1,
        "utility": 17186.4
    }
}