{
    "0": {
        "accuracy": 0.0,
        "avg_joules": 3.61416140228659,
        "battery": 31185.0,
        "comm_latency": 5.470907643379839,
        "delta_infer_battery": 34.45806341293407,
        "delta_train_battery": 79.0833603021957,
        "inference_latency": 6.173672385111014,
        "last_round": 0,
        "max_battery": 62370.0,
        "min_battery": 12474.0,
        "times_selected": 0,
        "total_inference_latency": 11.644580028490854,
        "total_train_latency": 23.99192479871288,
        "train_latency": 18.52101715533304,
        "trans_prob": 1,
        "utility": 31185.0
    },
    "1": {
        "accuracy": 0.0,
        "avg_joules": 3.5547753366832024,
        "battery": 54261.9,
        "comm_latency": 5.525782656530641,
        "delta_infer_battery": 39.42139608218884,
        "delta_train_battery": 93.72971325157049,
        "inference_latency": 7.638783330264443,
        "last_round": 0,
        "max_battery": 62370.0,
        "min_battery": 12474.0,
        "times_selected": 0,
        "total_inference_latency": 13.164565986795083,
        "total_train_latency": 28.44213264732397,
        "train_latency": 22.91634999079333,
        "trans_prob": 1,
        "utility": 54261.9
    },
    "2": {
        "accuracy": 0.0,
        "avg_joules": 3.1703698936348674,
        "battery": 45599.399999999994,
        "comm_latency": 5.292352520242429,
        "delta_infer_battery": 23.14252144542511,
        "delta_train_battery": 45.929519146398945,
        "inference_latency": 3.5937443366976125,
        "last_round": 0,
        "max_battery": 48510.0,
        "min_battery": 9702.0,
        "times_selected": 0,
        "total_inference_latency": 8.886096856940041,
        "total_train_latency": 16.073585530335265,
        "train_latency": 10.781233010092837,
        "trans_prob": 1,
        "utility": 45599.399999999994
    },
    "3": {
        "accuracy": 0.0,
        "avg_joules": 3.138233757054465,
        "battery": 40748.4,
        "comm_latency": 5.144981159022785,
        "delta_infer_battery": 28.318280948839828,
        "delta_train_battery": 62.111126500458305,
        "inference_latency": 5.384054880496908,
        "last_round": 0,
        "max_battery": 48510.0,
        "min_battery": 9702.0,
        "times_selected": 0,
        "total_inference_latency": 10.529036039519692,
        "total_train_latency": 21.29714580051351,
        "train_latency": 16.152164641490725,
        "trans_prob": 1,
        "utility": 40748.4
    },
    "4": {
        "accuracy": 0.0,
        "avg_joules": 3.7154363872135328,
        "battery": 68607.0,
        "comm_latency": 5.991437787694187,
        "delta_infer_battery": 26.307937112836328,
        "delta_train_battery": 52.3218275611468,
        "inference_latency": 3.5007853367959445,
        "last_round": 0,
        "max_battery": 69300.0,
        "min_battery": 13860.0,
        "times_selected": 0,
        "total_inference_latency": 9.492223124490131,
        "total_train_latency": 16.49379379808202,
        "train_latency": 10.502356010387834,
        "trans_prob": 1,
        "utility": 68607.0
    },
    "5": {
        "accuracy": 0.0,
        "avg_joules": 3.9704683583925156,
        "battery": 32155.199999999997,
        "comm_latency": 6.086032348267855,
        "delta_infer_battery": 35.001255491085274,
        "delta_train_battery": 77.98178284694652,
        "inference_latency": 5.4125261148362815,
        "last_round": 0,
        "max_battery": 55440.0,
        "min_battery": 11088.0,
        "times_selected": 0,
        "total_inference_latency": 11.498558463104136,
        "total_train_latency": 22.323610692776697,
        "train_latency": 16.237578344508844,
        "trans_prob": 1,
        "utility": 32155.199999999997
    },
    "6": {
        "accuracy": 0.0,
        "avg_joules": 3.9373573943481768,
        "battery": 46569.6,
        "comm_latency": 5.096315161488895,
        "delta_infer_battery": 21.75074573692946,
        "delta_train_battery": 42.62459789377769,
        "inference_latency": 2.6507438957422687,
        "last_round": 0,
        "max_battery": 48510.0,
        "min_battery": 9702.0,
        "times_selected": 0,
        "total_inference_latency": 7.747059057231164,
        "total_train_latency": 13.0485468487157,
        "train_latency": 7.9522316872268055,
        "trans_prob": 1,
        "utility": 46569.6
    },
    "7": {
        "accuracy": 0.0,
        "avg_joules": 3.4744404002991733,
        "battery": 54261.9,
        "comm_latency": 5.546034756407592,
        "delta_infer_battery": 17.912313405117388,
        "delta_train_battery": 29.112545896902446,
        "inference_latency": 1.6118038016741691,
        "last_round": 0,
        "max_battery": 62370.0,
        "min_battery": 12474.0,
        "times_selected": 0,
        "total_inference_latency": 7.157838558081761,
        "total_train_latency": 10.3814461614301,
        "train_latency": 4.835411405022508,
        "trans_prob": 1,
        "utility": 54261.9
    },
    "8": {
        "accuracy": 0.0,
        "avg_joules": 2.183924952251527,
        "battery": 36174.6,
        "comm_latency": 5.172751336997055,
        "delta_infer_battery": 20.693172209950394,
        "delta_train_battery": 39.11250069358425,
        "inference_latency": 4.217024139186736,
        "last_round": 0,
        "max_battery": 62370.0,
        "min_battery": 12474.0,
        "times_selected": 0,
        "total_inference_latency": 9.389775476183791,
        "total_train_latency": 17.823823754557264,
        "train_latency": 12.65107241756021,
        "trans_prob": 1,
        "utility": 36174.6
    },
    "9": {
        "accuracy": 0.0,
        "avg_joules": 2.788815093831072,
        "battery": 60498.9,
        "comm_latency": 6.124778343974516,
        "delta_infer_battery": 29.840300557576857,
        "delta_train_battery": 62.326885825483714,
        "inference_latency": 5.824442312394248,
        "last_round": 0,
        "max_battery": 62370.0,
        "min_battery": 12474.0,
        "times_selected": 0,
        "total_inference_latency": 11.949220656368762,
        "total_train_latency": 23.59810528115726,
        "train_latency": 17.473326937182744,
        "trans_prob": 1,
        "utility": 60498.9
    },
    "10": {
        "accuracy": 0.0,
        "avg_joules": 2.631633776815748,
        "battery": 18295.2,
        "comm_latency": 5.530738457786592,
        "delta_infer_battery": 27.335808018432672,
        "delta_train_battery": 57.45094530272554,
        "inference_latency": 5.721756870124213,
        "last_round": 0,
        "max_battery": 55440.0,
        "min_battery": 11088.0,
        "times_selected": 0,
        "total_inference_latency": 11.252495327910804,
        "total_train_latency": 22.696009068159228,
        "train_latency": 17.165270610372637,
        "trans_prob": 1,
        "utility": 18295.2
    },
    "11": {
        "accuracy": 0.0,
        "avg_joules": 3.853382612335324,
        "battery": 44352.0,
        "comm_latency": 5.2161325889918455,
        "delta_infer_battery": 30.98783929094742,
        "delta_train_battery": 69.80388917771846,
        "inference_latency": 5.036620262222905,
        "last_round": 0,
        "max_battery": 55440.0,
        "min_battery": 11088.0,
        "times_selected": 0,
        "total_inference_latency": 10.252752851214751,
        "total_train_latency": 20.32599337566056,
        "train_latency": 15.109860786668715,
        "trans_prob": 1,
        "utility": 44352.0
    },
    "12": {
        "accuracy": 0.0,
        "avg_joules": 4.683026582559975,
        "battery": 44282.7,
        "comm_latency": 5.805736813291063,
        "delta_infer_battery": 24.95917073575569,
        "delta_train_battery": 49.10004075625474,
        "inference_latency": 2.5774859052051817,
        "last_round": 0,
        "max_battery": 62370.0,
        "min_battery": 12474.0,
        "times_selected": 0,
        "total_inference_latency": 8.383222718496246,
        "total_train_latency": 13.538194528906608,
        "train_latency": 7.732457715615546,
        "trans_prob": 1,
        "utility": 44282.7
    },
    "13": {
        "accuracy": 0.0,
        "avg_joules": 4.495316821732278,
        "battery": 58212.0,
        "comm_latency": 4.9865462614238325,
        "delta_infer_battery": 43.817324107549844,
        "delta_train_battery": 109.31170692192772,
        "inference_latency": 7.284734915429109,
        "last_round": 0,
        "max_battery": 69300.0,
        "min_battery": 13860.0,
        "times_selected": 0,
        "total_inference_latency": 12.271281176852941,
        "total_train_latency": 26.84075100771116,
        "train_latency": 21.854204746287326,
        "trans_prob": 1,
        "utility": 58212.0
    },
    "14": {
        "accuracy": 0.0,
        "avg_joules": 4.491292687906489,
        "battery": 23076.9,
        "comm_latency": 5.029917682476045,
        "delta_infer_battery": 23.706911286322246,
        "delta_train_battery": 48.78789934877308,
        "inference_latency": 2.7921792015453977,
        "last_round": 0,
        "max_battery": 62370.0,
        "min_battery": 12474.0,
        "times_selected": 0,
        "total_inference_latency": 7.822096884021443,
        "total_train_latency": 13.406455287112237,
        "train_latency": 8.376537604636193,
        "trans_prob": 1,
        "utility": 23076.9
    },
    "15": {
        "accuracy": 0.0,
        "avg_joules": 4.549312111682072,
        "battery": 37699.200000000004,
        "comm_latency": 6.082744255001992,
        "delta_infer_battery": 49.09809206896706,
        "delta_train_battery": 120.28689171469233,
        "inference_latency": 7.824127900888711,
        "last_round": 0,
        "max_battery": 55440.0,
        "min_battery": 11088.0,
        "times_selected": 0,
        "total_inference_latency": 13.906872155890703,
        "total_train_latency": 29.555127957668123,
        "train_latency": 23.472383702666132,
        "trans_prob": 1,
        "utility": 37699.200000000004
    },
    "16": {
        "accuracy": 0.0,
        "avg_joules": 2.865882120261918,
        "battery": 25502.4,
        "comm_latency": 6.0902920905953275,
        "delta_infer_battery": 27.687893380243935,
        "delta_train_battery": 56.02278325848855,
        "inference_latency": 4.94348488340041,
        "last_round": 0,
        "max_battery": 55440.0,
        "min_battery": 11088.0,
        "times_selected": 0,
        "total_inference_latency": 11.033776973995739,
        "total_train_latency": 20.92074674079656,
        "train_latency": 14.830454650201231,
        "trans_prob": 1,
        "utility": 25502.4
    },
    "17": {
        "accuracy": 0.0,
        "avg_joules": 4.625234496822288,
        "battery": 27650.699999999997,
        "comm_latency": 5.417084271186384,
        "delta_infer_battery": 35.59170851292704,
        "delta_train_battery": 82.72327137471359,
        "inference_latency": 5.095045764076148,
        "last_round": 0,
        "max_battery": 48510.0,
        "min_battery": 9702.0,
        "times_selected": 0,
        "total_inference_latency": 10.512130035262532,
        "total_train_latency": 20.702221563414827,
        "train_latency": 15.285137292228445,
        "trans_prob": 1,
        "utility": 27650.699999999997
    },
    "18": {
        "accuracy": 0.0,
        "avg_joules": 4.119340576316121,
        "battery": 17463.6,
        "comm_latency": 4.992556521297946,
        "delta_infer_battery": 28.32147236445787,
        "delta_train_battery": 62.79746613881073,
        "inference_latency": 4.184649598114116,
        "last_round": 0,
        "max_battery": 48510.0,
        "min_battery": 9702.0,
        "times_selected": 0,
        "total_inference_latency": 9.177206119412062,
        "total_train_latency": 17.546505315640296,
        "train_latency": 12.553948794342348,
        "trans_prob": 1,
        "utility": 17463.6
    },
    "19": {
        "accuracy": 0.0,
        "avg_joules": 2.349702413411694,
        "battery": 43035.299999999996,
        "comm_latency": 5.609431022790069,
        "delta_infer_battery": 19.55108962749261,
        "delta_train_battery": 33.747395141289914,
        "inference_latency": 3.020873075834467,
        "last_round": 0,
        "max_battery": 62370.0,
        "min_battery": 12474.0,
        "times_selected": 0,
        "total_inference_latency": 8.630304098624537,
        "total_train_latency": 14.67205025029347,
        "train_latency": 9.0626192275034,
        "trans_prob": 1,
        "utility": 43035.299999999996
    },
    "20": {
        "accuracy": 0.0,
        "avg_joules": 2.1500718903466787,
        "battery": 27027.0,
        "comm_latency": 5.82200022852268,
        "delta_infer_battery": 29.88031485708758,
        "delta_train_battery": 63.79126355662204,
        "inference_latency": 7.886003452207042,
        "last_round": 0,
        "max_battery": 69300.0,
        "min_battery": 13860.0,
        "times_selected": 0,
        "total_inference_latency": 13.708003680729721,
        "total_train_latency": 29.480010585143805,
        "train_latency": 23.658010356621126,
        "trans_prob": 1,
        "utility": 27027.0
    },
    "21": {
        "accuracy": 0.0,
        "avg_joules": 2.143679924774437,
        "battery": 24324.3,
        "comm_latency": 5.559010607611395,
        "delta_infer_battery": 35.66807246748136,
        "delta_train_battery": 82.32221030464947,
        "inference_latency": 10.88178727103515,
        "last_round": 0,
        "max_battery": 62370.0,
        "min_battery": 12474.0,
        "times_selected": 0,
        "total_inference_latency": 16.440797878646546,
        "total_train_latency": 38.20437242071685,
        "train_latency": 32.64536181310545,
        "trans_prob": 1,
        "utility": 24324.3
    },
    "22": {
        "accuracy": 0.0,
        "avg_joules": 4.366760325756594,
        "battery": 38253.6,
        "comm_latency": 6.085015317306255,
        "delta_infer_battery": 34.529161905608596,
        "delta_train_battery": 76.57001770798601,
        "inference_latency": 4.813735202548966,
        "last_round": 0,
        "max_battery": 55440.0,
        "min_battery": 11088.0,
        "times_selected": 0,
        "total_inference_latency": 10.898750519855222,
        "total_train_latency": 20.526220924953154,
        "train_latency": 14.441205607646898,
        "trans_prob": 1,
        "utility": 38253.6
    },
    "23": {
        "accuracy": 0.0,
        "avg_joules": 2.8486776769602686,
        "battery": 32986.8,
        "comm_latency": 5.815180027264301,
        "delta_infer_battery": 22.729382682640413,
        "delta_train_battery": 42.368748726867736,
        "inference_latency": 3.4471021771027206,
        "last_round": 0,
        "max_battery": 48510.0,
        "min_battery": 9702.0,
        "times_selected": 0,
        "total_inference_latency": 9.262282204367022,
        "total_train_latency": 16.15648655857246,
        "train_latency": 10.341306531308161,
        "trans_prob": 1,
        "utility": 32986.8
    },
    "24": {
        "accuracy": 0.0,
        "avg_joules": 2.428465881883078,
        "battery": 31185.0,
        "comm_latency": 5.539818059509903,
        "delta_infer_battery": 32.78330079071426,
        "delta_train_battery": 73.7531101879188,
        "inference_latency": 8.435327360958388,
        "last_round": 0,
        "max_battery": 62370.0,
        "min_battery": 12474.0,
        "times_selected": 0,
        "total_inference_latency": 13.97514542046829,
        "total_train_latency": 30.845800142385066,
        "train_latency": 25.30598208287516,
        "trans_prob": 1,
        "utility": 31185.0
    },
    "25": {
        "accuracy": 0.0,
        "avg_joules": 3.974406252457429,
        "battery": 57519.0,
        "comm_latency": 5.470461766251528,
        "delta_infer_battery": 53.38896285161798,
        "delta_train_battery": 135.87803831269716,
        "inference_latency": 10.377534431724873,
        "last_round": 0,
        "max_battery": 69300.0,
        "min_battery": 13860.0,
        "times_selected": 0,
        "total_inference_latency": 15.847996197976402,
        "total_train_latency": 36.60306506142615,
        "train_latency": 31.13260329517462,
        "trans_prob": 1,
        "utility": 57519.0
    },
    "26": {
        "accuracy": 0.0,
        "avg_joules": 3.1332685922894847,
        "battery": 42966.0,
        "comm_latency": 5.799979501315893,
        "delta_infer_battery": 24.273482523216465,
        "delta_train_battery": 47.06853858380683,
        "inference_latency": 3.637584105729981,
        "last_round": 0,
        "max_battery": 69300.0,
        "min_battery": 13860.0,
        "times_selected": 0,
        "total_inference_latency": 9.437563607045874,
        "total_train_latency": 16.712731818505837,
        "train_latency": 10.912752317189943,
        "trans_prob": 1,
        "utility": 42966.0
    },
    "27": {
        "accuracy": 0.0,
        "avg_joules": 2.3085461355925423,
        "battery": 28690.2,
        "comm_latency": 5.802932451629367,
        "delta_infer_battery": 18.45198264958373,
        "delta_train_battery": 29.5909278635168,
        "inference_latency": 2.412545506930924,
        "last_round": 0,
        "max_battery": 62370.0,
        "min_battery": 12474.0,
        "times_selected": 0,
        "total_inference_latency": 8.21547795856029,
        "total_train_latency": 13.04056897242214,
        "train_latency": 7.237636520792772,
        "trans_prob": 1,
        "utility": 28690.2
    },
    "28": {
        "accuracy": 0.0,
        "avg_joules": 2.5788765740815425,
        "battery": 21483.0,
        "comm_latency": 5.819076251488269,
        "delta_infer_battery": 24.517002615121598,
        "delta_train_battery": 47.71430928875687,
        "inference_latency": 4.4975604700851015,
        "last_round": 0,
        "max_battery": 69300.0,
        "min_battery": 13860.0,
        "times_selected": 0,
        "total_inference_latency": 10.31663672157337,
        "total_train_latency": 19.311757661743574,
        "train_latency": 13.492681410255305,
        "trans_prob": 1,
        "utility": 21483.0
    },
    "29": {
        "accuracy": 0.0,
        "avg_joules": 3.6821411971440385,
        "battery": 16493.4,
        "comm_latency": 5.513609207201505,
        "delta_infer_battery": 75.94778002281055,
        "delta_train_battery": 203.36291518845695,
        "inference_latency": 17.301772032054718,
        "last_round": 0,
        "max_battery": 48510.0,
        "min_battery": 9702.0,
        "times_selected": 0,
        "total_inference_latency": 22.815381239256222,
        "total_train_latency": 57.418925303365654,
        "train_latency": 51.90531609616415,
        "trans_prob": 1,
        "utility": 16493.4
    },
    "30": {
        "accuracy": 0.0,
        "avg_joules": 2.604434838667285,
        "battery": 35550.899999999994,
        "comm_latency": 5.72551413657256,
        "delta_infer_battery": 22.513645774977924,
        "delta_train_battery": 42.11965455855161,
        "inference_latency": 3.7639660805655386,
        "last_round": 0,
        "max_battery": 62370.0,
        "min_battery": 12474.0,
        "times_selected": 0,
        "total_inference_latency": 9.489480217138098,
        "total_train_latency": 17.017412378269178,
        "train_latency": 11.291898241696616,
        "trans_prob": 1,
        "utility": 35550.899999999994
    },
    "31": {
        "accuracy": 0.0,
        "avg_joules": 2.9187433104560405,
        "battery": 60984.0,
        "comm_latency": 6.096109885141976,
        "delta_infer_battery": 24.469794217727863,
        "delta_train_battery": 46.34265476315321,
        "inference_latency": 3.7469654263649197,
        "last_round": 0,
        "max_battery": 69300.0,
        "min_battery": 13860.0,
        "times_selected": 0,
        "total_inference_latency": 9.843075311506896,
        "total_train_latency": 17.337006164236733,
        "train_latency": 11.240896279094759,
        "trans_prob": 1,
        "utility": 60984.0
    },
    "32": {
        "accuracy": 0.0,
        "avg_joules": 4.234769781555819,
        "battery": 31808.7,
        "comm_latency": 5.094458315757004,
        "delta_infer_battery": 53.782689226990804,
        "delta_train_battery": 138.72867275901132,
        "inference_latency": 10.029586956768647,
        "last_round": 0,
        "max_battery": 62370.0,
        "min_battery": 12474.0,
        "times_selected": 0,
        "total_inference_latency": 15.12404527252565,
        "total_train_latency": 35.18321918606294,
        "train_latency": 30.08876087030594,
        "trans_prob": 1,
        "utility": 31808.7
    },
    "33": {
        "accuracy": 0.0,
        "avg_joules": 3.4641048901369915,
        "battery": 52668.0,
        "comm_latency": 5.399707035551395,
        "delta_infer_battery": 20.26915745571261,
        "delta_train_battery": 36.832773129289635,
        "inference_latency": 2.3907497317325745,
        "last_round": 0,
        "max_battery": 55440.0,
        "min_battery": 11088.0,
        "times_selected": 0,
        "total_inference_latency": 7.7904567672839695,
        "total_train_latency": 12.57195623074912,
        "train_latency": 7.172249195197724,
        "trans_prob": 1,
        "utility": 52668.0
    },
    "34": {
        "accuracy": 0.0,
        "avg_joules": 3.066005299161978,
        "battery": 18849.600000000002,
        "comm_latency": 5.302654682068294,
        "delta_infer_battery": 32.3061220092288,
        "delta_train_battery": 73.37457923930317,
        "inference_latency": 6.697388494615371,
        "last_round": 0,
        "max_battery": 55440.0,
        "min_battery": 11088.0,
        "times_selected": 0,
        "total_inference_latency": 12.000043176683665,
        "total_train_latency": 25.394820165914407,
        "train_latency": 20.092165483846113,
        "trans_prob": 1,
        "utility": 18849.600000000002
    },
    "35": {
        "accuracy": 0.0,
        "avg_joules": 3.5213130425108368,
        "battery": 48648.6,
        "comm_latency": 5.8634543740103355,
        "delta_infer_battery": 27.852659437652246,
        "delta_train_battery": 57.524240892350846,
        "inference_latency": 4.213141674212182,
        "last_round": 0,
        "max_battery": 62370.0,
        "min_battery": 12474.0,
        "times_selected": 0,
        "total_inference_latency": 10.076596048222518,
        "total_train_latency": 18.502879396646883,
        "train_latency": 12.639425022636548,
        "trans_prob": 1,
        "utility": 48648.6
    },
    "36": {
        "accuracy": 0.0,
        "avg_joules": 2.1709037328959613,
        "battery": 38115.0,
        "comm_latency": 4.940618981300842,
        "delta_infer_battery": 18.074448498624378,
        "delta_train_battery": 32.28699721889739,
        "inference_latency": 3.273417541484816,
        "last_round": 0,
        "max_battery": 69300.0,
        "min_battery": 13860.0,
        "times_selected": 0,
        "total_inference_latency": 8.214036522785658,
        "total_train_latency": 14.76087160575529,
        "train_latency": 9.820252624454447,
        "trans_prob": 1,
        "utility": 38115.0
    },
    "37": {
        "accuracy": 0.0,
        "avg_joules": 3.2596713142844096,
        "battery": 35897.4,
        "comm_latency": 5.071658397588932,
        "delta_infer_battery": 38.576968512142955,
        "delta_train_battery": 93.21274225113402,
        "inference_latency": 8.380564859341526,
        "last_round": 0,
        "max_battery": 48510.0,
        "min_battery": 9702.0,
        "times_selected": 0,
        "total_inference_latency": 13.452223256930457,
        "total_train_latency": 30.21335297561351,
        "train_latency": 25.141694578024577,
        "trans_prob": 1,
        "utility": 35897.4
    },
    "38": {
        "accuracy": 0.0,
        "avg_joules": 3.3627560376272276,
        "battery": 29106.0,
        "comm_latency": 5.953270882967754,
        "delta_infer_battery": 23.22828163992658,
        "delta_train_battery": 43.25232219940291,
        "inference_latency": 2.977325791020713,
        "last_round": 0,
        "max_battery": 69300.0,
        "min_battery": 13860.0,
        "times_selected": 0,
        "total_inference_latency": 8.930596673988466,
        "total_train_latency": 14.885248256029893,
        "train_latency": 8.93197737306214,
        "trans_prob": 1,
        "utility": 29106.0
    },
    "39": {
        "accuracy": 0.0,
        "avg_joules": 2.664117914253939,
        "battery": 38808.00000000001,
        "comm_latency": 5.670425549700991,
        "delta_infer_battery": 38.25211449558834,
        "delta_train_battery": 89.5796540460926,
        "inference_latency": 9.633120830704309,
        "last_round": 0,
        "max_battery": 69300.0,
        "min_battery": 13860.0,
        "times_selected": 0,
        "total_inference_latency": 15.303546380405301,
        "total_train_latency": 34.569788041813915,
        "train_latency": 28.899362492112925,
        "trans_prob": 1,
        "utility": 38808.00000000001
    },
    "40": {
        "accuracy": 0.0,
        "avg_joules": 2.42628507733624,
        "battery": 58905.0,
        "comm_latency": 5.2161923726256,
        "delta_infer_battery": 61.07026751675299,
        "delta_train_battery": 160.0509084158013,
        "inference_latency": 20.397570306890067,
        "last_round": 0,
        "max_battery": 69300.0,
        "min_battery": 13860.0,
        "times_selected": 0,
        "total_inference_latency": 25.613762679515666,
        "total_train_latency": 66.40890329329581,
        "train_latency": 61.1927109206702,
        "trans_prob": 1,
        "utility": 58905.0
    },
    "41": {
        "accuracy": 0.0,
        "avg_joules": 4.79945550106806,
        "battery": 33679.8,
        "comm_latency": 5.227269022685307,
        "delta_infer_battery": 36.10007507937514,
        "delta_train_battery": 85.09115077740266,
        "inference_latency": 5.1038160148713905,
        "last_round": 0,
        "max_battery": 62370.0,
        "min_battery": 12474.0,
        "times_selected": 0,
        "total_inference_latency": 10.331085037556697,
        "total_train_latency": 20.53871706729948,
        "train_latency": 15.311448044614172,
        "trans_prob": 1,
        "utility": 33679.8
    },
    "42": {
        "accuracy": 0.0,
        "avg_joules": 3.6303479427860292,
        "battery": 64449.0,
        "comm_latency": 4.995220550989779,
        "delta_infer_battery": 26.94847234527498,
        "delta_train_battery": 58.66663778943031,
        "inference_latency": 4.368474584809898,
        "last_round": 0,
        "max_battery": 69300.0,
        "min_battery": 13860.0,
        "times_selected": 0,
        "total_inference_latency": 9.363695135799677,
        "total_train_latency": 18.100644305419475,
        "train_latency": 13.105423754429696,
        "trans_prob": 1,
        "utility": 64449.0
    },
    "43": {
        "accuracy": 0.0,
        "avg_joules": 2.7272729776553106,
        "battery": 26819.1,
        "comm_latency": 5.559022259194471,
        "delta_infer_battery": 35.414520647357776,
        "delta_train_battery": 81.56150311124986,
        "inference_latency": 8.460279341667798,
        "last_round": 0,
        "max_battery": 62370.0,
        "min_battery": 12474.0,
        "times_selected": 0,
        "total_inference_latency": 14.019301600862269,
        "total_train_latency": 30.939860284197866,
        "train_latency": 25.380838025003396,
        "trans_prob": 1,
        "utility": 26819.1
    },
    "44": {
        "accuracy": 0.0,
        "avg_joules": 3.91694592010205,
        "battery": 49272.3,
        "comm_latency": 5.102192737458256,
        "delta_infer_battery": 26.562897594867557,
        "delta_train_battery": 57.03495703028801,
        "inference_latency": 3.8897728047553124,
        "last_round": 0,
        "max_battery": 62370.0,
        "min_battery": 12474.0,
        "times_selected": 0,
        "total_inference_latency": 8.991965542213569,
        "total_train_latency": 16.771511151724194,
        "train_latency": 11.669318414265938,
        "trans_prob": 1,
        "utility": 49272.3
    },
    "45": {
        "accuracy": 0.0,
        "avg_joules": 4.5511190051336605,
        "battery": 37144.8,
        "comm_latency": 5.271742323064565,
        "delta_infer_battery": 36.00250098527735,
        "delta_train_battery": 84.60096704142538,
        "inference_latency": 5.3391776837003135,
        "last_round": 0,
        "max_battery": 55440.0,
        "min_battery": 11088.0,
        "times_selected": 0,
        "total_inference_latency": 10.610920006764879,
        "total_train_latency": 21.289275374165506,
        "train_latency": 16.01753305110094,
        "trans_prob": 1,
        "utility": 37144.8
    },
    "46": {
        "accuracy": 0.0,
        "avg_joules": 2.162454325527862,
        "battery": 45599.399999999994,
        "comm_latency": 5.707955713908542,
        "delta_infer_battery": 37.15899946451758,
        "delta_train_battery": 86.13367502379882,
        "inference_latency": 11.323863579714304,
        "last_round": 0,
        "max_battery": 48510.0,
        "min_battery": 9702.0,
        "times_selected": 0,
        "total_inference_latency": 17.031819293622846,
        "total_train_latency": 39.67954645305145,
        "train_latency": 33.97159073914291,
        "trans_prob": 1,
        "utility": 45599.399999999994
    },
    "47": {
        "accuracy": 0.0,
        "avg_joules": 2.153593562483386,
        "battery": 64449.0,
        "comm_latency": 5.364103287188743,
        "delta_infer_battery": 26.987543265097873,
        "delta_train_battery": 57.14601120017559,
        "inference_latency": 7.00189405755395,
        "last_round": 0,
        "max_battery": 69300.0,
        "min_battery": 13860.0,
        "times_selected": 0,
        "total_inference_latency": 12.365997344742693,
        "total_train_latency": 26.369785459850593,
        "train_latency": 21.00568217266185,
        "trans_prob": 1,
        "utility": 64449.0
    },
    "48": {
        "accuracy": 0.0,
        "avg_joules": 2.539385221198038,
        "battery": 19958.4,
        "comm_latency": 5.04889848307064,
        "delta_infer_battery": 22.091455724826744,
        "delta_train_battery": 43.8572579096466,
        "inference_latency": 4.285644021853274,
        "last_round": 0,
        "max_battery": 62370.0,
        "min_battery": 12474.0,
        "times_selected": 0,
        "total_inference_latency": 9.334542504923913,
        "total_train_latency": 17.905830548630462,
        "train_latency": 12.856932065559823,
        "trans_prob": 1,
        "utility": 19958.4
    },
    "49": {
        "accuracy": 0.0,
        "avg_joules": 4.256506418285369,
        "battery": 34442.1,
        "comm_latency": 5.085648264194469,
        "delta_infer_battery": 28.511934952409604,
        "delta_train_battery": 62.95552656420537,
        "inference_latency": 4.045993148727653,
        "last_round": 0,
        "max_battery": 48510.0,
        "min_battery": 9702.0,
        "times_selected": 0,
        "total_inference_latency": 9.131641412922122,
        "total_train_latency": 17.22362771037743,
        "train_latency": 12.137979446182959,
        "trans_prob": 1,
        "utility": 34442.1
    }
}